Metadata-Version: 2.1
Name: decitone
Version: 0.1.4
Summary: This package contains deep learning utilities files
Author: Asiedu Henry
Author-email: sensork82@gmail.com
